[{
    "id": 1,
    "publishType": "user",
    "publisher": {
      "avatar": "https://pic3.zhimg.com/aadd7b895_xs.jpg",
      "nickname": "Taro"
    },

    "graphic": {
      "text": "Taro 是一个开放式跨端跨框架解决方案，支持使用 React/Vue/Nerv 等框架来开发 微信 / 京东 / 百度 / 支付宝 / 字节跳动 / QQ 小程序 / H5 / RN 等应用。",
      "images": [
        "https://pic3.zhimg.com/aadd7b895_xs.jpg",
        "https://pic3.zhimg.com/aadd7b895_xs.jpg",
        "https://pic3.zhimg.com/aadd7b895_xs.jpg",
        "https://pic3.zhimg.com/aadd7b895_xs.jpg",
        "https://pic3.zhimg.com/aadd7b895_xs.jpg",
        "https://pic3.zhimg.com/aadd7b895_xs.jpg",
        "https://pic3.zhimg.com/aadd7b895_xs.jpg"
      ]
    },
    "isLiked": false,
    "publishTime": "3小时前"
  },
  {
    "id": 2,
    "publishType": "user",
    "publisher": {
      "avatar": "https://pic3.zhimg.com/aadd7b895_xs.jpg",
      "nickname": "Taro"
    },

    "graphic": {
      "text": "Taro 是一个开放式跨端跨框架解决方案，支持使用 React/Vue/Nerv 等框架来开发 微信 / 京东 / 百度 / 支付宝 / 字节跳动 / QQ 小程序 / H5 / RN 等应用。",
      "images": []
    },
    "isLiked": true,
    "publishTime": "3小时前"
  }, {
    "id": 3,
    "publishType": "user",
    "publisher": {
      "avatar": "https://pic3.zhimg.com/aadd7b895_xs.jpg",
      "nickname": "Taro"
    },

    "graphic": {
      "text": "Taro 是一个开放式跨端跨框架解决方案，支持使用 React/Vue/Nerv 等框架来开发 微信 / 京东 / 百度 / 支付宝 / 字节跳动 / QQ 小程序 / H5 / RN 等应用。",
      "images": []
    },
    "isLiked": false,
    "publishTime": "3小时前"
  }, {
    "id": 4,
    "publishType": "user",
    "publisher": {
      "avatar": "https://pic3.zhimg.com/aadd7b895_xs.jpg",
      "nickname": "Taro"
    },

    "graphic": {
      "text": "Taro 是一个开放式跨端跨框架解决方案，支持使用 React/Vue/Nerv 等框架来开发 微信 / 京东 / 百度 / 支付宝 / 字节跳动 / QQ 小程序 / H5 / RN 等应用。",
      "images": []
    },
    "isLiked": true,
    "publishTime": "3小时前"
  }, {
    "id": 5,
    "publishType": "user",
    "publisher": {
      "avatar": "https://pic3.zhimg.com/aadd7b895_xs.jpg",
      "nickname": "Taro"
    },

    "graphic": {
      "text": "Taro 是一个开放式跨端跨框架解决方案，支持使用 React/Vue/Nerv 等框架来开发 微信 / 京东 / 百度 / 支付宝 / 字节跳动 / QQ 小程序 / H5 / RN 等应用。",
      "images": []
    },
    "isLiked": false,
    "publishTime": "3小时前"
  },
  {
    "id": 6,
    "publishType": "user",
    "publisher": {
      "avatar": "https://pic3.zhimg.com/aadd7b895_xs.jpg",
      "nickname": "Taro"
    },

    "graphic": {
      "text": "Taro 是一个开放式跨端跨框架解决方案，支持使用 React/Vue/Nerv 等框架来开发 微信 / 京东 / 百度 / 支付宝 / 字节跳动 / QQ 小程序 / H5 / RN 等应用。",
      "images": []
    },
    "isLiked": false,
    "publishTime": "3小时前"
  },
  {
    "id": 7,
    "publishType": "user",
    "publisher": {
      "avatar": "https://pic3.zhimg.com/aadd7b895_xs.jpg",
      "nickname": "Taro"
    },

    "graphic": {
      "text": "Taro 是一个开放式跨端跨框架解决方案，支持使用 React/Vue/Nerv 等框架来开发 微信 / 京东 / 百度 / 支付宝 / 字节跳动 / QQ 小程序 / H5 / RN 等应用。",
      "images": []
    },
    "isLiked": false,
    "publishTime": "3小时前"
  },
  {
    "id": 8,
    "publishType": "user",
    "publisher": {
      "avatar": "https://pic3.zhimg.com/aadd7b895_xs.jpg",
      "nickname": "Taro"
    },

    "graphic": {
      "text": "Taro 是一个开放式跨端跨框架解决方案，支持使用 React/Vue/Nerv 等框架来开发 微信 / 京东 / 百度 / 支付宝 / 字节跳动 / QQ 小程序 / H5 / RN 等应用。",
      "images": []
    },
    "isLiked": false,
    "publishTime": "3小时前"
  }, {
    "id": 9,
    "publishType": "user",
    "publisher": {
      "avatar": "https://pic3.zhimg.com/aadd7b895_xs.jpg",
      "nickname": "Taro"
    },

    "graphic": {
      "text": "Taro 是一个开放式跨端跨框架解决方案，支持使用 React/Vue/Nerv 等框架来开发 微信 / 京东 / 百度 / 支付宝 / 字节跳动 / QQ 小程序 / H5 / RN 等应用。",
      "images": []
    },
    "isLiked": false,
    "publishTime": "3小时前"
  }, {
    "id": 10,
    "publishType": "user",
    "publisher": {
      "avatar": "https://pic3.zhimg.com/aadd7b895_xs.jpg",
      "nickname": "Taro"
    },

    "graphic": {
      "text": "Taro 是一个开放式跨端跨框架解决方案，支持使用 React/Vue/Nerv 等框架来开发 微信 / 京东 / 百度 / 支付宝 / 字节跳动 / QQ 小程序 / H5 / RN 等应用。",
      "images": []
    },
    "isLiked": false,
    "publishTime": "3小时前"
  }, {
    "id": 11,
    "publishType": "user",
    "publisher": {
      "avatar": "https://pic3.zhimg.com/aadd7b895_xs.jpg",
      "nickname": "Taro"
    },

    "graphic": {
      "text": "Taro 是一个开放式跨端跨框架解决方案，支持使用 React/Vue/Nerv 等框架来开发 微信 / 京东 / 百度 / 支付宝 / 字节跳动 / QQ 小程序 / H5 / RN 等应用。",
      "images": []
    },
    "isLiked": false,
    "publishTime": "3小时前"
  },
  {
    "id": 12,
    "publishType": "user",
    "publisher": {
      "avatar": "https://pic3.zhimg.com/aadd7b895_xs.jpg",
      "nickname": "Taro"
    },

    "graphic": {
      "text": "Taro 是一个开放式跨端跨框架解决方案，支持使用 React/Vue/Nerv 等框架来开发 微信 / 京东 / 百度 / 支付宝 / 字节跳动 / QQ 小程序 / H5 / RN 等应用。",
      "images": []
    },
    "isLiked": false,
    "publishTime": "3小时前"
  },{
    "id": 13,
    "publishType": "user",
    "publisher": {
      "avatar": "https://pic3.zhimg.com/aadd7b895_xs.jpg",
      "nickname": "Taro"
    },

    "graphic": {
      "text": "Taro 是一个开放式跨端跨框架解决方案，支持使用 React/Vue/Nerv 等框架来开发 微信 / 京东 / 百度 / 支付宝 / 字节跳动 / QQ 小程序 / H5 / RN 等应用。",
      "images": []
    },
    "isLiked": false,
    "publishTime": "3小时前"
  },
  {
    "id": 14,
    "publishType": "user",
    "publisher": {
      "avatar": "https://pic3.zhimg.com/aadd7b895_xs.jpg",
      "nickname": "Taro"
    },

    "graphic": {
      "text": "Taro 是一个开放式跨端跨框架解决方案，支持使用 React/Vue/Nerv 等框架来开发 微信 / 京东 / 百度 / 支付宝 / 字节跳动 / QQ 小程序 / H5 / RN 等应用。",
      "images": []
    },
    "isLiked": false,
    "publishTime": "3小时前"
  }, {
    "id": 15,
    "publishType": "user",
    "publisher": {
      "avatar": "https://pic3.zhimg.com/aadd7b895_xs.jpg",
      "nickname": "Taro"
    },

    "graphic": {
      "text": "Taro 是一个开放式跨端跨框架解决方案，支持使用 React/Vue/Nerv 等框架来开发 微信 / 京东 / 百度 / 支付宝 / 字节跳动 / QQ 小程序 / H5 / RN 等应用。",
      "images": []
    },
    "isLiked": false,
    "publishTime": "3小时前"
  }, {
    "id": 16,
    "publishType": "user",
    "publisher": {
      "avatar": "https://pic3.zhimg.com/aadd7b895_xs.jpg",
      "nickname": "Taro"
    },

    "graphic": {
      "text": "Taro 是一个开放式跨端跨框架解决方案，支持使用 React/Vue/Nerv 等框架来开发 微信 / 京东 / 百度 / 支付宝 / 字节跳动 / QQ 小程序 / H5 / RN 等应用。",
      "images": []
    },
    "isLiked": false,
    "publishTime": "3小时前"
  }, {
    "id": 17,
    "publishType": "user",
    "publisher": {
      "avatar": "https://pic3.zhimg.com/aadd7b895_xs.jpg",
      "nickname": "Taro"
    },

    "graphic": {
      "text": "Taro 是一个开放式跨端跨框架解决方案，支持使用 React/Vue/Nerv 等框架来开发 微信 / 京东 / 百度 / 支付宝 / 字节跳动 / QQ 小程序 / H5 / RN 等应用。",
      "images": []
    },
    "isLiked": false,
    "publishTime": "3小时前"
  },
  {
    "id": 18,
    "publishType": "user",
    "publisher": {
      "avatar": "https://pic3.zhimg.com/aadd7b895_xs.jpg",
      "nickname": "Taro"
    },

    "graphic": {
      "text": "Taro 是一个开放式跨端跨框架解决方案，支持使用 React/Vue/Nerv 等框架来开发 微信 / 京东 / 百度 / 支付宝 / 字节跳动 / QQ 小程序 / H5 / RN 等应用。",
      "images": []
    },
    "isLiked": false,
    "publishTime": "3小时前"
  },{
    "id": 19,
    "publishType": "user",
    "publisher": {
      "avatar": "https://pic3.zhimg.com/aadd7b895_xs.jpg",
      "nickname": "Taro"
    },

    "graphic": {
      "text": "Taro 是一个开放式跨端跨框架解决方案，支持使用 React/Vue/Nerv 等框架来开发 微信 / 京东 / 百度 / 支付宝 / 字节跳动 / QQ 小程序 / H5 / RN 等应用。",
      "images": []
    },
    "isLiked": false,
    "publishTime": "3小时前"
  },
  {
    "id": 20,
    "publishType": "user",
    "publisher": {
      "avatar": "https://pic3.zhimg.com/aadd7b895_xs.jpg",
      "nickname": "Taro"
    },

    "graphic": {
      "text": "Taro 是一个开放式跨端跨框架解决方案，支持使用 React/Vue/Nerv 等框架来开发 微信 / 京东 / 百度 / 支付宝 / 字节跳动 / QQ 小程序 / H5 / RN 等应用。",
      "images": []
    },
    "isLiked": false,
    "publishTime": "3小时前"
  }, {
    "id": 1,
    "publishType": "user",
    "publisher": {
      "avatar": "https://pic3.zhimg.com/aadd7b895_xs.jpg",
      "nickname": "Taro"
    },

    "graphic": {
      "text": "Taro 是一个开放式跨端跨框架解决方案，支持使用 React/Vue/Nerv 等框架来开发 微信 / 京东 / 百度 / 支付宝 / 字节跳动 / QQ 小程序 / H5 / RN 等应用。",
      "images": []
    },
    "isLiked": false,
    "publishTime": "3小时前"
  }, {
    "id": 1,
    "publishType": "user",
    "publisher": {
      "avatar": "https://pic3.zhimg.com/aadd7b895_xs.jpg",
      "nickname": "Taro"
    },

    "graphic": {
      "text": "Taro 是一个开放式跨端跨框架解决方案，支持使用 React/Vue/Nerv 等框架来开发 微信 / 京东 / 百度 / 支付宝 / 字节跳动 / QQ 小程序 / H5 / RN 等应用。",
      "images": []
    },
    "isLiked": false,
    "publishTime": "3小时前"
  }, {
    "id": 1,
    "publishType": "user",
    "publisher": {
      "avatar": "https://pic3.zhimg.com/aadd7b895_xs.jpg",
      "nickname": "Taro"
    },

    "graphic": {
      "text": "Taro 是一个开放式跨端跨框架解决方案，支持使用 React/Vue/Nerv 等框架来开发 微信 / 京东 / 百度 / 支付宝 / 字节跳动 / QQ 小程序 / H5 / RN 等应用。",
      "images": []
    },
    "isLiked": false,
    "publishTime": "3小时前"
  },
  {
    "id": 21,
    "publishType": "user",
    "publisher": {
      "avatar": "https://pic3.zhimg.com/aadd7b895_xs.jpg",
      "nickname": "Taro"
    },

    "graphic": {
      "text": "Taro 是一个开放式跨端跨框架解决方案，支持使用 React/Vue/Nerv 等框架来开发 微信 / 京东 / 百度 / 支付宝 / 字节跳动 / QQ 小程序 / H5 / RN 等应用。",
      "images": []
    },
    "isLiked": false,
    "publishTime": "3小时前"
  }
]
